greenprompt/__init__.py
greenprompt/analytics.py
greenprompt/api.py
greenprompt/cli.py
greenprompt/constants.py
greenprompt/core.py
greenprompt/dbconn.py
greenprompt/samplerMac.py
greenprompt/scoreBasic.py
greenprompt/setup.py
greenprompt/sysUsage.py
greenprompt/templates/dashboard.html
greenprompt-0.1.1.dist-info/LICENSE
greenprompt-0.1.1.dist-info/METADATA
greenprompt-0.1.1.dist-info/WHEEL
greenprompt-0.1.1.dist-info/entry_points.txt
greenprompt-0.1.1.dist-info/RECORD
