Metadata-Version: 2.3
Name: greenprompt
Version: 0.1.1
Summary: A green prompt tool to estimate energy usage of LLM prompts
License: MIT
Keywords: llm,energy,monitoring,ollama,cli
Author: Uday udapra@gmail.com
Requires-Python: >=3.9,<4.0
Classifier: License :: OSI Approved :: MIT License
Classifier: Operating System :: MacOS
Classifier: Programming Language :: Python :: 3
Classifier: Programming Language :: Python :: 3.9
Classifier: Programming Language :: Python :: 3.10
Classifier: Programming Language :: Python :: 3.11
Classifier: Programming Language :: Python :: 3.12
Classifier: Programming Language :: Python :: 3.13
Requires-Dist: Flask (>=3.1.0,<4.0.0)
Requires-Dist: flask-cors (>=6.0.0,<7.0.0)
Requires-Dist: nbformat (>=5.10.4,<6.0.0)
Requires-Dist: nltk (>=3.9.1,<4.0.0)
Requires-Dist: openai (>=1.77.0,<2.0.0)
Requires-Dist: pandas (>=2.2.3,<3.0.0)
Requires-Dist: plotly (>=6.1.1,<7.0.0)
Requires-Dist: pre-commit (>=4.2.0,<5.0.0)
Requires-Dist: psutil (>=7.0.0,<8.0.0)
Requires-Dist: py-cpuinfo (>=9.0.0,<10.0.0)
Requires-Dist: requests (>=2.32.3,<3.0.0)
Requires-Dist: ruff (>=0.11.11,<0.12.0)
Requires-Dist: statsmodels (>=0.14.4,<0.15.0)
Requires-Dist: tiktoken (>=0.9.0,<0.10.0)
Requires-Dist: twine (>=6.1.0,<7.0.0)
Project-URL: Homepage, https://github.com/uday1201/greenprompt
Project-URL: Repository, https://github.com/uday1201/greenprompt
